emmett/__init__.py
emmett/__main__.py
emmett/__version__.py
emmett/_internal.py
emmett/_reloader.py
emmett/_shortcuts.py
emmett/app.py
emmett/cache.py
emmett/cli.py
emmett/ctx.py
emmett/datastructures.py
emmett/debug.py
emmett/extensions.py
emmett/forms.py
emmett/helpers.py
emmett/html.py
emmett/http.py
emmett/locals.py
emmett/parsers.py
emmett/pipeline.py
emmett/security.py
emmett/serializers.py
emmett/sessions.py
emmett/testing.py
emmett/utils.py
emmett/asgi/__init__.py
emmett/asgi/handlers.py
emmett/asgi/wrappers.py
emmett/assets/__init__.py
emmett/assets/helpers.js
emmett/assets/jquery.min.js
emmett/assets/jquery.min.map
emmett/assets/debug/__init__.py
emmett/assets/debug/shBrushPython.js
emmett/assets/debug/shCore.css
emmett/assets/debug/shCore.js
emmett/assets/debug/shTheme.css
emmett/assets/debug/view.css
emmett/assets/debug/view.html
emmett/language/__init__.py
emmett/language/helpers.py
emmett/language/translator.py
emmett/libs/__init__.py
emmett/libs/contenttype.py
emmett/libs/portalocker.py
emmett/orm/__init__.py
emmett/orm/_patches.py
emmett/orm/adapters.py
emmett/orm/apis.py
emmett/orm/base.py
emmett/orm/connection.py
emmett/orm/errors.py
emmett/orm/geo.py
emmett/orm/helpers.py
emmett/orm/models.py
emmett/orm/objects.py
emmett/orm/transactions.py
emmett/orm/wrappers.py
emmett/orm/engines/__init__.py
emmett/orm/engines/postgres.py
emmett/orm/engines/sqlite.py
emmett/orm/migrations/__init__.py
emmett/orm/migrations/base.py
emmett/orm/migrations/commands.py
emmett/orm/migrations/engine.py
emmett/orm/migrations/exceptions.py
emmett/orm/migrations/generation.py
emmett/orm/migrations/helpers.py
emmett/orm/migrations/migration.tmpl
emmett/orm/migrations/operations.py
emmett/orm/migrations/revisions.py
emmett/orm/migrations/scripts.py
emmett/orm/migrations/utils.py
emmett/routing/__init__.py
emmett/routing/response.py
emmett/routing/router.py
emmett/routing/routes.py
emmett/routing/rules.py
emmett/routing/urls.py
emmett/rsgi/__init__.py
emmett/rsgi/handlers.py
emmett-2.7.1.dist-info/METADATA
emmett-2.7.1.dist-info/WHEEL
emmett-2.7.1.dist-info/entry_points.txt
emmett-2.7.1.dist-info/licenses/LICENSE
emmett-2.7.1.dist-info/RECORD
